MANIFEST.in
README.txt
setup.py
docs/HISTORY.txt
src/zeam/__init__.py
src/zeam.form.table.egg-info/PKG-INFO
src/zeam.form.table.egg-info/SOURCES.txt
src/zeam.form.table.egg-info/dependency_links.txt
src/zeam.form.table.egg-info/namespace_packages.txt
src/zeam.form.table.egg-info/not-zip-safe
src/zeam.form.table.egg-info/requires.txt
src/zeam.form.table.egg-info/top_level.txt
src/zeam/form/__init__.py
src/zeam/form/table/__init__.py
src/zeam/form/table/actions.py
src/zeam/form/table/configure.zcml
src/zeam/form/table/form.py
src/zeam/form/table/ftesting.zcml
src/zeam/form/table/interfaces.py
src/zeam/form/table/select.py
src/zeam/form/table/testing.py
src/zeam/form/table/default_templates/subtableformtemplate.cpt
src/zeam/form/table/select_templates/selectfieldwidget.cpt
src/zeam/form/table/tests/__init__.py
src/zeam/form/table/tests/forms.txt
src/zeam/form/table/tests/test_doctest.py