Metadata-Version: 1.0
Name: zeam.form.table
Version: 1.0.1
Summary: Form as table, to edit more than one content at a time
Home-page: http://pypi.python.org/pypi/zeam.form.table
Author: Sylvain Viollon
Author-email: thefunny@gmail.com
License: BSD
Keywords: zeam form table
Platform: UNKNOWN
Classifier: Programming Language :: Python
Classifier: Topic :: Software Development :: Libraries :: Python Modules
